ThreeJsRumenZhinan/README.md
ThreeJsRumenZhinan/__init__.py
ThreeJsRumenZhinan/__main__.py
ThreeJsRumenZhinan/file.epub
ThreeJsRumenZhinan/index.html
ThreeJsRumenZhinan/css/__init__.py
ThreeJsRumenZhinan/css/annotations.css
ThreeJsRumenZhinan/css/main.css
ThreeJsRumenZhinan/css/normalize.css
ThreeJsRumenZhinan/css/popup.css
ThreeJsRumenZhinan/font/__init__.py
ThreeJsRumenZhinan/font/fontello.eot
ThreeJsRumenZhinan/font/fontello.svg
ThreeJsRumenZhinan/font/fontello.ttf
ThreeJsRumenZhinan/font/fontello.woff
ThreeJsRumenZhinan/img/__init__.py
ThreeJsRumenZhinan/img/annotator-glyph-sprite.png
ThreeJsRumenZhinan/img/annotator-icon-sprite.png
ThreeJsRumenZhinan/img/apple-touch-icon.png
ThreeJsRumenZhinan/img/cancelfullscreen.png
ThreeJsRumenZhinan/img/close.png
ThreeJsRumenZhinan/img/fullscreen.png
ThreeJsRumenZhinan/img/loader.gif
ThreeJsRumenZhinan/img/menu-icon.png
ThreeJsRumenZhinan/img/save.png
ThreeJsRumenZhinan/img/saved.png
ThreeJsRumenZhinan/img/settings-s.png
ThreeJsRumenZhinan/img/settings.png
ThreeJsRumenZhinan/img/star.png
ThreeJsRumenZhinan/js/__init__.py
ThreeJsRumenZhinan/js/epub.js
ThreeJsRumenZhinan/js/epub.min.js
ThreeJsRumenZhinan/js/epub.min.map
ThreeJsRumenZhinan/js/hooks.min.js
ThreeJsRumenZhinan/js/hooks.min.map
ThreeJsRumenZhinan/js/reader.js
ThreeJsRumenZhinan/js/reader.js.map
ThreeJsRumenZhinan/js/reader.min.js
ThreeJsRumenZhinan/js/reader.min.map
ThreeJsRumenZhinan/js/hooks/__init__.py
ThreeJsRumenZhinan/js/hooks/extensions/__init__.py
ThreeJsRumenZhinan/js/hooks/extensions/highlight.js
ThreeJsRumenZhinan/js/libs/__init__.py
ThreeJsRumenZhinan/js/libs/jquery.min.js
ThreeJsRumenZhinan/js/libs/localforage.min.js
ThreeJsRumenZhinan/js/libs/screenfull.js
ThreeJsRumenZhinan/js/libs/screenfull.min.js
ThreeJsRumenZhinan/js/libs/zip.min.js
ThreeJsRumenZhinan/js/plugins/__init__.py
ThreeJsRumenZhinan/js/plugins/hypothesis.js
ThreeJsRumenZhinan/js/plugins/search.js
three_js_rumen_zhinan-2024.3.2.0.dist-info/METADATA
three_js_rumen_zhinan-2024.3.2.0.dist-info/WHEEL
three_js_rumen_zhinan-2024.3.2.0.dist-info/entry_points.txt
three_js_rumen_zhinan-2024.3.2.0.dist-info/top_level.txt
three_js_rumen_zhinan-2024.3.2.0.dist-info/RECORD
